[{
  "username": "Ms. Madyson Daugherty",
  "email": "Dawson50@gmail.com",
  "imageUrl": "https://s3.amazonaws.com/uifaces/faces/twitter/dc_user/128.jpg",
  "description": "I'll navigate the optical FTP panel, that should interface the TCP array!",
  "coverBackground": "https://picsum.photos/640/480",
  "location": "Philippines",
  "price": "42.00"
}, {
  "username": "Elwin Kerluke",
  "email": "Tamara48@yahoo.com",
  "imageUrl": "https://s3.amazonaws.com/uifaces/faces/twitter/guiiipontes/128.jpg",
  "description": "I'll parse the cross-platform PNG application, that should pixel the USB driver!",
  "coverBackground": "https://picsum.photos/640/480",
  "location": "Estonia",
  "price": "99.00"
}, {
  "username": "Nasir Littel",
  "email": "Vaughn_Grant31@gmail.com",
  "imageUrl": "https://s3.amazonaws.com/uifaces/faces/twitter/spbroma/128.jpg",
  "description": "Try to program the HDD driver, maybe it will override the wireless circuit!",
  "coverBackground": "https://picsum.photos/640/480",
  "location": "Sri Lanka",
  "price": "36.00"
}, {
  "username": "Freida Abshire",
  "email": "Eula.Mann@gmail.com",
  "imageUrl": "https://s3.amazonaws.com/uifaces/faces/twitter/conspirator/128.jpg",
  "description": "If we copy the microchip, we can get to the PNG feed through the 1080p AGP system!",
  "coverBackground": "https://picsum.photos/640/480",
  "location": "Australia",
  "price": "31.00"
}, {
  "username": "Major Senger",
  "email": "Joey.Schultz@gmail.com",
  "imageUrl": "https://s3.amazonaws.com/uifaces/faces/twitter/xravil/128.jpg",
  "description": "If we compress the array, we can get to the SQL system through the haptic SMS driver!",
  "coverBackground": "https://picsum.photos/640/480",
  "location": "Mongolia",
  "price": "28.00"
}]